<?xml version="1.0" encoding="UTF-8"?>
<configuration scan="true">

    <!-- 로그 저장 경로 설정 -->
    <property name="LOG_PATH" value="./logs"/>

    <!-- 로그 출력 패턴 설정 -->
    <property name="LOG_PATTERN"
              value="%d{yyyy-MM-dd HH:mm:ss.SSS} [%thread] %-5level %logger{36} - %msg%n"/>

    <!-- 콘솔 로그 출력 설정 -->
    <appender name="CONSOLE" class="ch.qos.logback.core.ConsoleAppender">
        <encoder>
            <pattern>${LOG_PATTERN}</pattern>
        </encoder>
    </appender>

    <!-- 파일 로그 출력 설정 (일별 롤링) -->
    <appender name="FILE" class="ch.qos.logback.core.rolling.RollingFileAppender">
        <file>${LOG_PATH}/application.log</file>

        <rollingPolicy class="ch.qos.logback.core.rolling.TimeBasedRollingPolicy">
            <!-- 매일 로그 파일 생성 -->
            <fileNamePattern>${LOG_PATH}/application.%d{yyyy-MM-dd}.log</fileNamePattern>
            <!-- 최대 보관 일수 -->
            <maxHistory>30</maxHistory>
        </rollingPolicy>

        <encoder>
            <pattern>${LOG_PATTERN}</pattern>
        </encoder>
    </appender>

    <!-- Spring Security 로그 레벨 제한 -->
    <logger name="org.springframework.security" level="WARN"/>
    <logger name="org.springframework.web.filter" level="WARN"/>
    <logger name="org.springframework.security.oauth2" level="WARN"/>

    <!-- 루트 로거 설정 -->
    <root level="INFO">
        <appender-ref ref="CONSOLE"/>
        <appender-ref ref="FILE"/>
    </root>
</configuration>